README.rst
setup.py
forge/__init__.py
forge/__version__.py
forge/attribute_manager.py
forge/bound_signature_adapter.py
forge/caller_info.py
forge/class_mock.py
forge/class_mock_handle.py
forge/comparators.py
forge/constants.py
forge/debug.py
forge/dtypes.py
forge/exceptions.py
forge/forge.py
forge/forge_test_case.py
forge/function_call.py
forge/handle.py
forge/mock_handle.py
forge/mock_object.py
forge/python3_compat.py
forge/queue.py
forge/queued_group.py
forge/queued_node.py
forge/queued_object.py
forge/replacer.py
forge/sentinel.py
forge/setattr.py
forge/signature.py
forge/stub.py
forge/stub_handle.py
forge/stub_manager.py
forge/utils.py
forge/wildcard_mock_handle.py
forge/wildcard_mock_object.py
pyforge.egg-info/PKG-INFO
pyforge.egg-info/SOURCES.txt
pyforge.egg-info/dependency_links.txt
pyforge.egg-info/requires.txt
pyforge.egg-info/top_level.txt
tests/ut_utils/__init__.py