Metadata-Version: 1.1
Name: pyforge
Version: 1.1.0
Summary: Python mocking framework
Home-page: http://github.com/vmalloc/pyforge
Author: Rotem Yaari
Author-email: vmalloc@gmail.com
License: BSD
Platform: UNKNOWN
Classifier: Development Status :: 4 - Beta
Classifier: Intended Audience :: Developers
Classifier: License :: OSI Approved :: BSD License
Classifier: Programming Language :: Python :: 2.6
Classifier: Topic :: Software Development :: Libraries :: Python Modules
Classifier: Topic :: Software Development :: Testing
